Workbook

Sheet SUMMARY
A1: Master coverage summary
A2: Counts update from the MASTER sheet. Generated 2026-10-31. "Concept covered?" is measured by comparing each item's distinctive terms with the book text (see LEGEND).
A4: Source | B4: Items | C4: Covered | D4: Partly covered | E4: Not covered | F4: Not measured | G4: Excluded by you | H4: No teaching content | I4: Not applicable | J4: Measurable items | K4: % Covered (of measurable) | L4: % Covered or partly
A5: Course repo file | B5: =COUNTIFS(MASTER!$B:$B,$A5) -> 464 | C5: =COUNTIFS(MASTER!$B:$B,$A5,MASTER!$H:$H,C$4) -> 225 | D5: =COUNTIFS(MASTER!$B:$B,$A5,MASTER!$H:$H,D$4) -> 27 | E5: =COUNTIFS(MASTER!$B:$B,$A5,MASTER!$H:$H,E$4) -> 4 | F5: =COUNTIFS(MASTER!$B:$B,$A5,MASTER!$H:$H,F$4) -> 0 | G5: =COUNTIFS(MASTER!$B:$B,$A5,MASTER!$H:$H,G$4) -> 67 | H5: =COUNTIFS(MASTER!$B:$B,$A5,MASTER!$H:$H,H$4) -> 141 | I5: =COUNTIFS(MASTER!$B:$B,$A5,MASTER!$H:$H,I$4) -> 0 | J5: =C5+D5+E5+F5 -> 256 | K5: =IF(J5=0,0,C5/J5) -> 0.87890625 | L5: =IF(J5=0,0,(C5+D5)/J5) -> 0.984375
A6: LangChain docs | B6: =COUNTIFS(MASTER!$B:$B,$A6) -> 196 | C6: =COUNTIFS(MASTER!$B:$B,$A6,MASTER!$H:$H,C$4) -> 39 | D6: =COUNTIFS(MASTER!$B:$B,$A6,MASTER!$H:$H,D$4) -> 10 | E6: =COUNTIFS(MASTER!$B:$B,$A6,MASTER!$H:$H,E$4) -> 1 | F6: =COUNTIFS(MASTER!$B:$B,$A6,MASTER!$H:$H,F$4) -> 0 | G6: =COUNTIFS(MASTER!$B:$B,$A6,MASTER!$H:$H,G$4) -> 26 | H6: =COUNTIFS(MASTER!$B:$B,$A6,MASTER!$H:$H,H$4) -> 3 | I6: =COUNTIFS(MASTER!$B:$B,$A6,MASTER!$H:$H,I$4) -> 117 | J6: =C6+D6+E6+F6 -> 50 | K6: =IF(J6=0,0,C6/J6) -> 0.78 | L6: =IF(J6=0,0,(C6+D6)/J6) -> 0.98
A7: MCP docs | B7: =COUNTIFS(MASTER!$B:$B,$A7) -> 100 | C7: =COUNTIFS(MASTER!$B:$B,$A7,MASTER!$H:$H,C$4) -> 48 | D7: =COUNTIFS(MASTER!$B:$B,$A7,MASTER!$H:$H,D$4) -> 44 | E7: =COUNTIFS(MASTER!$B:$B,$A7,MASTER!$H:$H,E$4) -> 7 | F7: =COUNTIFS(MASTER!$B:$B,$A7,MASTER!$H:$H,F$4) -> 0 | G7: =COUNTIFS(MASTER!$B:$B,$A7,MASTER!$H:$H,G$4) -> 0 | H7: =COUNTIFS(MASTER!$B:$B,$A7,MASTER!$H:$H,H$4) -> 1 | I7: =COUNTIFS(MASTER!$B:$B,$A7,MASTER!$H:$H,I$4) -> 0 | J7: =C7+D7+E7+F7 -> 99 | K7: =IF(J7=0,0,C7/J7) -> 0.48484848 | L7: =IF(J7=0,0,(C7+D7)/J7) -> 0.92929293
A8: Pydantic docs | B8: =COUNTIFS(MASTER!$B:$B,$A8) -> 56 | C8: =COUNTIFS(MASTER!$B:$B,$A8,MASTER!$H:$H,C$4) -> 13 | D8: =COUNTIFS(MASTER!$B:$B,$A8,MASTER!$H:$H,D$4) -> 25 | E8: =COUNTIFS(MASTER!$B:$B,$A8,MASTER!$H:$H,E$4) -> 12 | F8: =COUNTIFS(MASTER!$B:$B,$A8,MASTER!$H:$H,F$4) -> 0 | G8: =COUNTIFS(MASTER!$B:$B,$A8,MASTER!$H:$H,G$4) -> 0 | H8: =COUNTIFS(MASTER!$B:$B,$A8,MASTER!$H:$H,H$4) -> 5 | I8: =COUNTIFS(MASTER!$B:$B,$A8,MASTER!$H:$H,I$4) -> 1 | J8: =C8+D8+E8+F8 -> 50 | K8: =IF(J8=0,0,C8/J8) -> 0.26 | L8: =IF(J8=0,0,(C8+D8)/J8) -> 0.76
A9: Meridian slides | B9: =COUNTIFS(MASTER!$B:$B,$A9) -> 40 | C9: =COUNTIFS(MASTER!$B:$B,$A9,MASTER!$H:$H,C$4) -> 26 | D9: =COUNTIFS(MASTER!$B:$B,$A9,MASTER!$H:$H,D$4) -> 13 | E9: =COUNTIFS(MASTER!$B:$B,$A9,MASTER!$H:$H,E$4) -> 0 | F9: =COUNTIFS(MASTER!$B:$B,$A9,MASTER!$H:$H,F$4) -> 0 | G9: =COUNTIFS(MASTER!$B:$B,$A9,MASTER!$H:$H,G$4) -> 1 | H9: =COUNTIFS(MASTER!$B:$B,$A9,MASTER!$H:$H,H$4) -> 0 | I9: =COUNTIFS(MASTER!$B:$B,$A9,MASTER!$H:$H,I$4) -> 0 | J9: =C9+D9+E9+F9 -> 39 | K9: =IF(J9=0,0,C9/J9) -> 0.66666667 | L9: =IF(J9=0,0,(C9+D9)/J9) -> 1
A10: Craft page | B10: =COUNTIFS(MASTER!$B:$B,$A10) -> 21 | C10: =COUNTIFS(MASTER!$B:$B,$A10,MASTER!$H:$H,C$4) -> 13 | D10: =COUNTIFS(MASTER!$B:$B,$A10,MASTER!$H:$H,D$4) -> 0 | E10: =COUNTIFS(MASTER!$B:$B,$A10,MASTER!$H:$H,E$4) -> 2 | F10: =COUNTIFS(MASTER!$B:$B,$A10,MASTER!$H:$H,F$4) -> 0 | G10: =COUNTIFS(MASTER!$B:$B,$A10,MASTER!$H:$H,G$4) -> 0 | H10: =COUNTIFS(MASTER!$B:$B,$A10,MASTER!$H:$H,H$4) -> 6 | I10: =COUNTIFS(MASTER!$B:$B,$A10,MASTER!$H:$H,I$4) -> 0 | J10: =C10+D10+E10+F10 -> 15 | K10: =IF(J10=0,0,C10/J10) -> 0.86666667 | L10: =IF(J10=0,0,(C10+D10)/J10) -> 0.86666667
A11: Craft attachment | B11: =COUNTIFS(MASTER!$B:$B,$A11) -> 42 | C11: =COUNTIFS(MASTER!$B:$B,$A11,MASTER!$H:$H,C$4) -> 31 | D11: =COUNTIFS(MASTER!$B:$B,$A11,MASTER!$H:$H,D$4) -> 0 | E11: =COUNTIFS(MASTER!$B:$B,$A11,MASTER!$H:$H,E$4) -> 5 | F11: =COUNTIFS(MASTER!$B:$B,$A11,MASTER!$H:$H,F$4) -> 0 | G11: =COUNTIFS(MASTER!$B:$B,$A11,MASTER!$H:$H,G$4) -> 0 | H11: =COUNTIFS(MASTER!$B:$B,$A11,MASTER!$H:$H,H$4) -> 6 | I11: =COUNTIFS(MASTER!$B:$B,$A11,MASTER!$H:$H,I$4) -> 0 | J11: =C11+D11+E11+F11 -> 36 | K11: =IF(J11=0,0,C11/J11) -> 0.86111111 | L11: =IF(J11=0,0,(C11+D11)/J11) -> 0.86111111
A12: Instructor site | B12: =COUNTIFS(MASTER!$B:$B,$A12) -> 16 | C12: =COUNTIFS(MASTER!$B:$B,$A12,MASTER!$H:$H,C$4) -> 14 | D12: =COUNTIFS(MASTER!$B:$B,$A12,MASTER!$H:$H,D$4) -> 0 | E12: =COUNTIFS(MASTER!$B:$B,$A12,MASTER!$H:$H,E$4) -> 0 | F12: =COUNTIFS(MASTER!$B:$B,$A12,MASTER!$H:$H,F$4) -> 0 | G12: =COUNTIFS(MASTER!$B:$B,$A12,MASTER!$H:$H,G$4) -> 0 | H12: =COUNTIFS(MASTER!$B:$B,$A12,MASTER!$H:$H,H$4) -> 2 | I12: =COUNTIFS(MASTER!$B:$B,$A12,MASTER!$H:$H,I$4) -> 0 | J12: =C12+D12+E12+F12 -> 14 | K12: =IF(J12=0,0,C12/J12) -> 1 | L12: =IF(J12=0,0,(C12+D12)/J12) -> 1
A13: Other repo | B13: =COUNTIFS(MASTER!$B:$B,$A13) -> 2 | C13: =COUNTIFS(MASTER!$B:$B,$A13,MASTER!$H:$H,C$4) -> 1 | D13: =COUNTIFS(MASTER!$B:$B,$A13,MASTER!$H:$H,D$4) -> 0 | E13: =COUNTIFS(MASTER!$B:$B,$A13,MASTER!$H:$H,E$4) -> 1 | F13: =COUNTIFS(MASTER!$B:$B,$A13,MASTER!$H:$H,F$4) -> 0 | G13: =COUNTIFS(MASTER!$B:$B,$A13,MASTER!$H:$H,G$4) -> 0 | H13: =COUNTIFS(MASTER!$B:$B,$A13,MASTER!$H:$H,H$4) -> 0 | I13: =COUNTIFS(MASTER!$B:$B,$A13,MASTER!$H:$H,I$4) -> 0 | J13: =C13+D13+E13+F13 -> 2 | K13: =IF(J13=0,0,C13/J13) -> 0.5 | L13: =IF(J13=0,0,(C13+D13)/J13) -> 0.5
A14: TOTAL | B14: =SUM(B5:B13) -> 937 | C14: =SUM(C5:C13) -> 410 | D14: =SUM(D5:D13) -> 119 | E14: =SUM(E5:E13) -> 32 | F14: =SUM(F5:F13) -> 0 | G14: =SUM(G5:G13) -> 94 | H14: =SUM(H5:H13) -> 164 | I14: =SUM(I5:I13) -> 118 | J14: =SUM(J5:J13) -> 561 | K14: =IF(J14=0,0,C14/J14) -> 0.73083779 | L14: =IF(J14=0,0,(C14+D14)/J14) -> 0.942959
A17: Work still to do (Action status)
A19: Source | B19: To do | C19: Needs your decision | D19: Done | E19: Not needed
A20: Course repo file | B20: =COUNTIFS(MASTER!$B:$B,$A20,MASTER!$O:$O,B$19) -> 31 | C20: =COUNTIFS(MASTER!$B:$B,$A20,MASTER!$O:$O,C$19) -> 0 | D20: =COUNTIFS(MASTER!$B:$B,$A20,MASTER!$O:$O,D$19) -> 225 | E20: =COUNTIFS(MASTER!$B:$B,$A20,MASTER!$O:$O,E$19) -> 208
A21: LangChain docs | B21: =COUNTIFS(MASTER!$B:$B,$A21,MASTER!$O:$O,B$19) -> 11 | C21: =COUNTIFS(MASTER!$B:$B,$A21,MASTER!$O:$O,C$19) -> 0 | D21: =COUNTIFS(MASTER!$B:$B,$A21,MASTER!$O:$O,D$19) -> 39 | E21: =COUNTIFS(MASTER!$B:$B,$A21,MASTER!$O:$O,E$19) -> 146
A22: MCP docs | B22: =COUNTIFS(MASTER!$B:$B,$A22,MASTER!$O:$O,B$19) -> 20 | C22: =COUNTIFS(MASTER!$B:$B,$A22,MASTER!$O:$O,C$19) -> 31 | D22: =COUNTIFS(MASTER!$B:$B,$A22,MASTER!$O:$O,D$19) -> 48 | E22: =COUNTIFS(MASTER!$B:$B,$A22,MASTER!$O:$O,E$19) -> 1
A23: Pydantic docs | B23: =COUNTIFS(MASTER!$B:$B,$A23,MASTER!$O:$O,B$19) -> 36 | C23: =COUNTIFS(MASTER!$B:$B,$A23,MASTER!$O:$O,C$19) -> 1 | D23: =COUNTIFS(MASTER!$B:$B,$A23,MASTER!$O:$O,D$19) -> 13 | E23: =COUNTIFS(MASTER!$B:$B,$A23,MASTER!$O:$O,E$19) -> 6
A24: Meridian slides | B24: =COUNTIFS(MASTER!$B:$B,$A24,MASTER!$O:$O,B$19) -> 13 | C24: =COUNTIFS(MASTER!$B:$B,$A24,MASTER!$O:$O,C$19) -> 0 | D24: =COUNTIFS(MASTER!$B:$B,$A24,MASTER!$O:$O,D$19) -> 26 | E24: =COUNTIFS(MASTER!$B:$B,$A24,MASTER!$O:$O,E$19) -> 1
A25: Craft page | B25: =COUNTIFS(MASTER!$B:$B,$A25,MASTER!$O:$O,B$19) -> 0 | C25: =COUNTIFS(MASTER!$B:$B,$A25,MASTER!$O:$O,C$19) -> 2 | D25: =COUNTIFS(MASTER!$B:$B,$A25,MASTER!$O:$O,D$19) -> 13 | E25: =COUNTIFS(MASTER!$B:$B,$A25,MASTER!$O:$O,E$19) -> 6
A26: Craft attachment | B26: =COUNTIFS(MASTER!$B:$B,$A26,MASTER!$O:$O,B$19) -> 5 | C26: =COUNTIFS(MASTER!$B:$B,$A26,MASTER!$O:$O,C$19) -> 0 | D26: =COUNTIFS(MASTER!$B:$B,$A26,MASTER!$O:$O,D$19) -> 31 | E26: =COUNTIFS(MASTER!$B:$B,$A26,MASTER!$O:$O,E$19) -> 6
A27: Instructor site | B27: =COUNTIFS(MASTER!$B:$B,$A27,MASTER!$O:$O,B$19) -> 0 | C27: =COUNTIFS(MASTER!$B:$B,$A27,MASTER!$O:$O,C$19) -> 0 | D27: =COUNTIFS(MASTER!$B:$B,$A27,MASTER!$O:$O,D$19) -> 14 | E27: =COUNTIFS(MASTER!$B:$B,$A27,MASTER!$O:$O,E$19) -> 2
A28: Other repo | B28: =COUNTIFS(MASTER!$B:$B,$A28,MASTER!$O:$O,B$19) -> 0 | C28: =COUNTIFS(MASTER!$B:$B,$A28,MASTER!$O:$O,C$19) -> 1 | D28: =COUNTIFS(MASTER!$B:$B,$A28,MASTER!$O:$O,D$19) -> 1 | E28: =COUNTIFS(MASTER!$B:$B,$A28,MASTER!$O:$O,E$19) -> 0
A29: TOTAL | B29: =SUM(B20:B28) -> 116 | C29: =SUM(C20:C28) -> 35 | D29: =SUM(D20:D28) -> 410 | E29: =SUM(E20:E28) -> 376

Sheet MASTER
A1: ID | B1: Source | C1: Group | D1: Item | E1: Path or URL | F1: What it teaches | G1: Read status | H1: Concept covered? | I1: Overlap score | J1: Method | K1: Where covered (book:chapter and matches) | L1: Missing concepts (evidence) | M1: Priority | N1: Action needed | O1: Action status | P1: Last checked | Q1: Notes
A2: R-001 | B2: Course repo file | C2: (repo root) | D2: .gitattributes | E2: .gitattributes | F2: .gitattributes | G2: Ignored | H2: No teaching content | J2: Measured: shared terms with the books | M2: Medium | N2: None | O2: Not needed | P2: 2026-10-31 | Q2: lock file, log, config or archive
A3: R-002 | B3: Course repo file | C3: .github | D3: path-audit.yml | E3: .github/workflows/path-audit.yml | F3: Fails a push / PR that would break `git clone` or `git pull` for students on Windows, macOS or Linux | G3: Read properly | H3: No teaching content | J3: Measured: shared terms with the books | M3: Medium | N3: None | O3: Not needed | P3: 2026-10-31 | Q3: too little text to measure
A4: R-003 | B4: Course repo file | C4: (repo root) | D4: .gitignore | E4: .gitignore | F4: .gitignore | G4: Ignored | H4: No teaching content | J4: Measured: shared terms with the books | M4: Medium | N4: None | O4: Not needed | P4: 2026-10-31 | Q4: lock file, log, config or archive
A5: R-004 | B5: Course repo file | C5: (repo root) | D5: COLAB_NOTEBOOKS.md | E5: COLAB_NOTEBOOKS.md | F5: 📓 Live Colab Notebooks — Full Index | G5: Read properly | H5: Covered | I5: 1 | J5: Measured: shared terms with the books | K5: agentic-ai:ch5 (4), agentic-ai:ch10 (3), agentic-ai:ch12 (3) | M5: Medium | N5: None | O5: Done | P5: 2026-10-31
A6: R-005 | B6: Course repo file | C6: Complete MCP | D6: Commands.txt | E6: Complete MCP/Commands.txt | F6: install uv if you don't have it | G6: Looked through | H6: No teaching content | J6: Measured: shared terms with the books | M6: Medium | N6: None | O6: Not needed | P6: 2026-10-31 | Q6: too little text to measure
A7: R-006 | B7: Course repo file | C7: Complete MCP | D7: README.md | E7: Complete MCP/MCP-Precoded/README.md | F7: Building Your First MCP Server — RecipeBox, Two Ways | G7: Looked through | H7: Covered | I7: 0.84615385 | J7: Measured: shared terms with the books | K7: agentic-ai:ch14 (6), agentic-ai:ch11 (6), agentic-ai:ch16 (4) | L7: part4_building_first_server_notebook, stdio_server | M7: Medium | N7: None | O7: Done | P7: 2026-10-31
A8: R-007 | B8: Course repo file | C8: Complete MCP | D8: recipebox_fastmcp.py | E8: Complete MCP/MCP-Precoded/recipebox_fastmcp.py | F8: RecipeBox -- the EXACT same server as recipebox_lowlevel.py, rebuilt with | G8: Looked through | H8: Covered | I8: 1 | J8: Measured: shared terms with the books | K8: agentic-ai:ch14 (10), agentic-ai:ch11 (4), agentic-ai:ch16 (3) | M8: Medium | N8: None | O8: Done | P8: 2026-10-31
A9: R-008 | B9: Course repo file | C9: Complete MCP | D9: recipebox_lowlevel.py | E9: Complete MCP/MCP-Precoded/recipebox_lowlevel.py | F9: RecipeBox -- built with the RAW, low-level official `mcp` SDK. | G9: Looked through | H9: Covered | I9: 0.86666667 | J9: Measured: shared terms with the books | K9: agentic-ai:ch14 (11), agentic-ai:ch16 (6), agentic-ai:ch11 (6) | L9: create_initialization_options, stdio_server | M9: Medium | N9: None | O9: Done | P9: 2026-10-31
A10: R-009 | B10: Course repo file | C10: Complete MCP | D10: .gitignore | E10: Complete MCP/McpWarmup/.gitignore | F10: .gitignore | G10: Ignored | H10: No teaching content | J10: Measured: shared terms with the books | M10: Medium | N10: None | O10: Not needed | P10: 2026-10-31 | Q10: lock file, log, config or archive
A11: R-010 | B11: Course repo file | C11: Complete MCP | D11: .python-version | E11: Complete MCP/McpWarmup/.python-version | F11: .python-version | G11: Ignored | H11: No teaching content | J11: Measured: shared terms with the books | M11: Medium | N11: None | O11: Not needed | P11: 2026-10-31 | Q11: lock file, log, config or archive
A12: R-011 | B12: Course repo file | C12: Complete MCP | D12: README.md | E12: Complete MCP/McpWarmup/README.md | F12: README.md | G12: Looked through | H12: No teaching content | J12: Measured: shared terms with the books | M12: Medium | N12: None | O12: Not needed | P12: 2026-10-31 | Q12: too little text to measure
A13: R-012 | B13: Course repo file | C13: Complete MCP | D13: mcp_server_with_primitives.py | E13: Complete MCP/McpWarmup/mcp_server_with_primitives.py | F13: mcp_server_with_primitives.py | G13: Looked through | H13: Covered | I13: 1 | J13: Measured: shared terms with the books | K13: agentic-ai:ch12 (6) | M13: Medium | N13: None | O13: Done | P13: 2026-10-31
A14: R-013 | B14: Course repo file | C14: Complete MCP | D14: pyproject.toml | E14: Complete MCP/McpWarmup/pyproject.toml | F14: pyproject.toml | G14: Ignored | H14: No teaching content | J14: Measured: shared terms with the books | M14: Medium | N14: None | O14: Not needed | P14: 2026-10-31 | Q14: lock file, log, config or archive
A15: R-014 | B15: Course repo file | C15: Complete MCP | D15: server.py | E15: Complete MCP/McpWarmup/server.py | F15: server.py | G15: Looked through | H15: No teaching content | J15: Measured: shared terms with the books | K15: agentic-ai:ch11 (2), agentic-ai:ch16 (2) | M15: Medium | N15: None | O15: Not needed | P15: 2026-10-31 | Q15: too little text to measure
A16: R-015 | B16: Course repo file | C16: Complete MCP | D16: server_with_auth.py | E16: Complete MCP/McpWarmup/server_with_auth.py | F16: server_with_auth.py | G16: Looked through | H16: Covered | I16: 1 | J16: Measured: shared terms with the books | K16: agentic-ai:ch16 (24), agentic-ai:ch18 (9), agentic-ai:ch11 (8) | M16: Medium | N16: None | O16: Done | P16: 2026-10-31
A17: R-016 | B17: Course repo file | C17: Complete MCP | D17: __init__.py | E17: Complete MCP/McpWarmup/src/mcp_warmup/__init__.py | F17: __init__.py | G17: Ignored | H17: No teaching content | J17: Measured: shared terms with the books | M17: Medium | N17: None | O17: Not needed | P17: 2026-10-31 | Q17: lock file, log, config or archive
A18: R-017 | B18: Course repo file | C18: Complete MCP | D18: uv.lock | E18: Complete MCP/McpWarmup/uv.lock | F18: uv.lock | G18: Ignored | H18: No teaching content | J18: Measured: shared terms with the books | M18: Medium | N18: None | O18: Not needed | P18: 2026-10-31 | Q18: lock file, log, config or archive
A19: R-018 | B19: Course repo file | C19: Complete MCP | D19: mcp-client-and-advanced.zip | E19: Complete MCP/TimeTrackProject/mcp-client-and-advanced.zip | F19: mcp-client-and-advanced.zip | G19: Ignored | H19: No teaching content | J19: Measured: shared terms with the books | K19: agentic-ai:ch15, agentic-ai:ch16 | M19: Medium | N19: None | O19: Not needed | P19: 2026-10-31 | Q19: lock file, log, config or archive
A20: R-019 | B20: Course repo file | C20: Complete MCP | D20: MCP_PROTOCOL_CHANGES_SUMMARY.txt | E20: Complete MCP/TimeTrackProject/mcp-client-and-advanced/MCP_PROTOCOL_CHANGES_SUMMARY.txt | F20: MCP_PROTOCOL_CHANGES_SUMMARY.txt | G20: Looked through | H20: Covered | I20: 1 | J20: Measured: shared terms with the books | K20: agentic-ai:ch16 (6), agentic-ai:ch17 (6), agentic-ai:ch14 (2) | M20: Medium | N20: None | O20: Done | P20: 2026-10-31
A21: R-020 | B21: Course repo file | C21: Complete MCP | D21: README.md | E21: Complete MCP/TimeTrackProject/mcp-client-and-advanced/README.md | F21: Building Your Own MCP Client — Complete, Numbered, Self-Contained | G21: Read properly | H21: Covered | I21: 0.95238095 | J21: Measured: shared terms with the books | K21: agentic-ai:ch16 (20), agentic-ai:ch17 (11), agentic-ai:ch13 (6) | L21: client_project | M21: Medium | N21: None | O21: Done | P21: 2026-10-31
A22: R-021 | B22: Course repo file | C22: Complete MCP | D22: 01_raw_client.py | E22: Complete MCP/TimeTrackProject/mcp-client-and-advanced/client/01_raw_client.py | F22: 01 -- THE RAW CLIENT | G22: Read properly | H22: Covered | I22: 1 | J22: Measured: shared terms with the books | K22: agentic-ai:ch16 (20), agentic-ai:ch15 (8), agentic-ai:ch11 (8) | M22: Medium | N22: None | O22: Done | P22: 2026-10-31
A23: R-022 | B23: Course repo file | C23: Complete MCP | D23: 02_fastmcp_client_explained.py | E23: Complete MCP/TimeTrackProject/mcp-client-and-advanced/client/02_fastmcp_client_explained.py | F23: 02 -- THE EASY CLIENT, EXPLAINED STEP BY STEP | G23: Read properly | H23: Covered | I23: 1 | J23: Measured: shared terms with the books | K23: agentic-ai:ch16 (19), agentic-ai:ch14 (13), agentic-ai:ch17 (12) | M23: Medium | N23: None | O23: Done | P23: 2026-10-31
A24: R-023 | B24: Course repo file | C24: Complete MCP | D24: 03_fastmcp_client_http.py | E24: Complete MCP/TimeTrackProject/mcp-client-and-advanced/client/03_fastmcp_client_http.py | F24: 03 -- CONNECTING TO A REAL, DEPLOYED SERVER OVER HTTP | G24: Read properly | H24: Covered | I24: 1 | J24: Measured: shared terms with the books | K24: agentic-ai:ch16 (16), agentic-ai:ch11 (10), agentic-ai:ch17 (9) | M24: Medium | N24: None | O24: Done | P24: 2026-10-31
A25: R-024 | B25: Course repo file | C25: Complete MCP | D25: 04_agent_loop.py | E25: Complete MCP/TimeTrackProject/mcp-client-and-advanced/client/04_agent_loop.py | F25: 04 -- A REAL AGENT LOOP, NO FRAMEWORK | G25: Read properly | H25: Covered | I25: 1 | J25: Measured: shared terms with the books | K25: agentic-ai:ch16 (26), agentic-ai:ch17 (10), agentic-ai:ch11 (7) | M25: Medium | N25: None | O25: Done | P25: 2026-10-31
A26: R-025 | B26: Course repo file | C26: Complete MCP | D26: 05_sampling_demo.py | E26: Complete MCP/TimeTrackProject/mcp-client-and-advanced/client/05_sampling_demo.py | F26: 05 -- SUMMARIZE_WEEK: THE SERVER CALLS AN LLM DIRECTLY | G26: Read properly | H26: Covered | I26: 1 | J26: Measured: shared terms with the books | K26: agentic-ai:ch16 (18), agentic-ai:ch17 (15), agentic-ai:ch11 (11) | M26: Medium | N26: None | O26: Done | P26: 2026-10-31
A27: R-026 | B27: Course repo file | C27: Complete MCP | D27: 06_elicitation_demo.py | E27: Complete MCP/TimeTrackProject/mcp-client-and-advanced/client/06_elicitation_demo.py | F27: 06 -- ELICITATION: THE SERVER ASKS A REAL QUESTION | G27: Read properly | H27: Covered | I27: 1 | J27: Measured: shared terms with the books | K27: agentic-ai:ch17 (17), agentic-ai:ch16 (14), agentic-ai:ch13 (8) | M27: Medium | N27: None | O27: Done | P27: 2026-10-31
A28: R-027 | B28: Course repo file | C28: Complete MCP | D28: 07_ping_and_errors.py | E28: Complete MCP/TimeTrackProject/mcp-client-and-advanced/client/07_ping_and_errors.py | F28: 07 -- PING AND A REAL ERROR | G28: Read properly | H28: Covered | I28: 1 | J28: Measured: shared terms with the books | K28: agentic-ai:ch17 (11), agentic-ai:ch16 (8), agentic-ai:ch12 (7) | M28: Medium | N28: None | O28: Done | P28: 2026-10-31
A29: R-028 | B29: Course repo file | C29: Complete MCP | D29: 08_timeout_and_cancellation.py | E29: Complete MCP/TimeTrackProject/mcp-client-and-advanced/client/08_timeout_and_cancellation.py | F29: 08 -- TIMEOUT, WHICH TRIGGERS A REAL CANCELLATION | G29: Read properly | H29: Covered | I29: 1 | J29: Measured: shared terms with the books | K29: agentic-ai:ch17 (7), agentic-ai:ch16 (7), agentic-ai:ch12 (5) | M29: Medium | N29: None | O29: Done | P29: 2026-10-31
A30: R-029 | B30: Course repo file | C30: Complete MCP | D30: 09_progress_notifications.py | E30: Complete MCP/TimeTrackProject/mcp-client-and-advanced/client/09_progress_notifications.py | F30: 09 -- PROGRESS NOTIFICATIONS, WATCHED LIVE | G30: Read properly | H30: Covered | I30: 1 | J30: Measured: shared terms with the books | K30: agentic-ai:ch17 (9), agentic-ai:ch16 (6), agentic-ai:ch18 (5) | M30: Medium | N30: None | O30: Done | P30: 2026-10-31
A31: R-030 | B31: Course repo file | C31: Complete MCP | D31: database.py | E31: Complete MCP/TimeTrackProject/mcp-client-and-advanced/database.py | F31: TimeTrack's persistence layer -- SQLite, shared by every tool in this | G31: Read properly | H31: Covered | I31: 1 | J31: Measured: shared terms with the books | K31: agentic-ai:ch16 (35), agentic-ai:ch15 (17), agentic-ai:ch17 (12) | M31: Medium | N31: None | O31: Done | P31: 2026-10-31
A32: R-031 | B32: Course repo file | C32: Complete MCP | D32: main.py | E32: Complete MCP/TimeTrackProject/mcp-client-and-advanced/main.py | F32: main.py -- the COMPLETE TimeTrack server used by every file in client/. | G32: Read properly | H32: Covered | I32: 1 | J32: Measured: shared terms with the books | K32: agentic-ai:ch16 (33), agentic-ai:ch17 (22), agentic-ai:ch15 (16) | M32: Medium | N32: None | O32: Done | P32: 2026-10-31
A33: R-032 | B33: Course repo file | C33: Complete MCP | D33: pyproject.toml | E33: Complete MCP/TimeTrackProject/mcp-client-and-advanced/pyproject.toml | F33: pyproject.toml | G33: Ignored | H33: No teaching content | J33: Measured: shared terms with the books | K33: agentic-ai:ch15, agentic-ai:ch16 | M33: Medium | N33: None | O33: Not needed | P33: 2026-10-31 | Q33: lock file, log, config or archive
A34: R-033 | B34: Course repo file | C34: Complete MCP | D34: timetrack.db | E34: Complete MCP/TimeTrackProject/mcp-client-and-advanced/timetrack.db | F34: timetrack.db | G34: Ignored | H34: No teaching content | J34: Measured: shared terms with the books | K34: agentic-ai:ch15, agentic-ai:ch16 | M34: Medium | N34: None | O34: Not needed | P34: 2026-10-31 | Q34: lock file, log, config or archive
A35: R-034 | B35: Course repo file | C35: Complete MCP | D35: uv.lock | E35: Complete MCP/TimeTrackProject/mcp-client-and-advanced/uv.lock | F35: uv.lock | G35: Ignored | H35: No teaching content | J35: Measured: shared terms with the books | K35: agentic-ai:ch15, agentic-ai:ch16 | M35: Medium | N35: None | O35: Not needed | P35: 2026-10-31 | Q35: lock file, log, config or archive
A36: R-035 | B36: Course repo file | C36: Complete MCP | D36: .python-version | E36: Complete MCP/TimeTrackProject/timetrack mcp server/.python-version | F36: .python-version | G36: Ignored | H36: No teaching content | J36: Measured: shared terms with the books | K36: agentic-ai:ch15, agentic-ai:ch16 | M36: Medium | N36: None | O36: Not needed | P36: 2026-10-31 | Q36: lock file, log, config or archive
A37: R-036 | B37: Course repo file | C37: Complete MCP | D37: README.md | E37: Complete MCP/TimeTrackProject/timetrack mcp server/README.md | F37: TimeTrack | G37: Read properly | H37: Covered | I37: 0.9375 | J37: Measured: shared terms with the books | K37: agentic-ai:ch15 (14), agentic-ai:ch16 (13), agentic-ai:ch17 (5) | L37: heading: checklist complete setup | M37: Medium | N37: None | O37: Done | P37: 2026-10-31
A38: R-037 | B38: Course repo file | C38: Complete MCP | D38: database.py | E38: Complete MCP/TimeTrackProject/timetrack mcp server/database.py | F38: TimeTrack's persistence layer -- SQLite, shared by the website and the MCP | G38: Looked through | H38: Covered | I38: 0.97297297 | J38: Measured: shared terms with the books | K38: agentic-ai:ch16 (36), agentic-ai:ch15 (17), agentic-ai:ch17 (12) | L38: execute_query | M38: Medium | N38: None | O38: Done | P38: 2026-10-31
A39: R-038 | B39: Course repo file | C39: Complete MCP | D39: dummy.py | E39: Complete MCP/TimeTrackProject/timetrack mcp server/dummy.py | F39: Dummy Calculator MCP server -- a minimal example for deploying to Horizon. | G39: Looked through | H39: Covered | J39: Measured: shared terms with the books | K39: agentic-ai:ch17 (2), agentic-ai:ch18 (2), agentic-ai:ch16 (2) | M39: Medium | N39: None | O39: Done | P39: 2026-10-31 | Q39: too little text to measure; a chapter links to it
A40: R-039 | B40: Course repo file | C40: Complete MCP | D40: main.py | E40: Complete MCP/TimeTrackProject/timetrack mcp server/main.py | F40: TimeTrack -- one running application, two front doors onto the same | G40: Looked through | H40: Covered | I40: 0.76666667 | J40: Measured: shared terms with the books | K40: agentic-ai:ch15 (21), agentic-ai:ch16 (20), agentic-ai:ch17 (4) | L40: serve_index, api_list_entries, fileresponse, api_project_summary, api_list_projects, api_get_timesheet, api_log_entry | M40: Medium | N40: None | O40: Done | P40: 2026-10-31
A41: R-040 | B41: Course repo file | C41: Complete MCP | D41: main_to_understand.py | E41: Complete MCP/TimeTrackProject/timetrack mcp server/main_to_understand.py | F41: main_to_understand.py | G41: Looked through | H41: Covered | I41: 0.75 | J41: Measured: shared terms with the books | K41: agentic-ai:ch16 (24), agentic-ai:ch15 (22), agentic-ai:ch17 (7) | L41: main_to_understand, get_schema, execute_query_dynamically, api_list_all_entries, execute_query, api_project_summary, api_list_projects, api_get_timesheet, api_log_entry | M41: Medium | N41: None | O41: Done | P41: 2026-10-31
A42: R-041 | B42: Course repo file | C42: Complete MCP | D42: README.md | E42: Complete MCP/TimeTrackProject/timetrack mcp server/mcp-client-and-advanced/README.md | F42: Building Your Own MCP Client — Complete, Numbered, Self-Contained | G42: Looked through | H42: Covered | I42: 0.88235294 | J42: Measured: shared terms with the books | K42: agentic-ai:ch16 (15), agentic-ai:ch17 (9), agentic-ai:ch11 (4) | L42: _fastmcp_client, client_project | M42: Medium | N42: None | O42: Done | P42: 2026-10-31
A43: R-042 | B43: Course repo file | C43: Complete MCP | D43: 01_raw_client.py | E43: Complete MCP/TimeTrackProject/timetrack mcp server/mcp-client-and-advanced/client/01_raw_client.py | F43: 01 -- THE RAW CLIENT | G43: Looked through | H43: Covered | I43: 1 | J43: Measured: shared terms with the books | K43: agentic-ai:ch16 (20), agentic-ai:ch15 (8), agentic-ai:ch11 (8) | M43: Medium | N43: None | O43: Done | P43: 2026-10-31
A44: R-043 | B44: Course repo file | C44: Complete MCP | D44: 02_fastmcp_client.py | E44: Complete MCP/TimeTrackProject/timetrack mcp server/mcp-client-and-advanced/client/02_fastmcp_client.py | F44: 02 -- THE EASY CLIENT | G44: Looked through | H44: Covered | I44: 1 | J44: Measured: shared terms with the books | K44: agentic-ai:ch16 (7), agentic-ai:ch11 (5), agentic-ai:ch14 (5) | M44: Medium | N44: None | O44: Done | P44: 2026-10-31
A45: R-044 | B45: Course repo file | C45: Complete MCP | D45: 03_agent_loop.py | E45: Complete MCP/TimeTrackProject/timetrack mcp server/mcp-client-and-advanced/client/03_agent_loop.py | F45: 03 -- A REAL AGENT LOOP, NO FRAMEWORK | G45: Looked through | H45: Covered | I45: 1 | J45: Measured: shared terms with the books | K45: agentic-ai:ch16 (26), agentic-ai:ch17 (10), agentic-ai:ch11 (7) | M45: Medium | N45: None | O45: Done | P45: 2026-10-31
A46: R-045 | B46: Course repo file | C46: Complete MCP | D46: 04_sampling_demo.py | E46: Complete MCP/TimeTrackProject/timetrack mcp server/mcp-client-and-advanced/client/04_sampling_demo.py | F46: 04 -- SAMPLING: THE SERVER BORROWS THE CLIENT'S LLM | G46: Looked through | H46: Covered | I46: 1 | J46: Measured: shared terms with the books | K46: agentic-ai:ch16 (17), agentic-ai:ch17 (15), agentic-ai:ch11 (7) | M46: Medium | N46: None | O46: Done | P46: 2026-10-31
A47: R-046 | B47: Course repo file | C47: Complete MCP | D47: 05_elicitation_demo.py | E47: Complete MCP/TimeTrackProject/timetrack mcp server/mcp-client-and-advanced/client/05_elicitation_demo.py | F47: 05 -- ELICITATION: THE SERVER ASKS A REAL QUESTION | G47: Looked through | H47: Covered | I47: 1 | J47: Measured: shared terms with the books | K47: agentic-ai:ch17 (15), agentic-ai:ch16 (12), agentic-ai:ch13 (6) | M47: Medium | N47: None | O47: Done | P47: 2026-10-31
A48: R-047 | B48: Course repo file | C48: Complete MCP | D48: 06_ping_and_errors.py | E48: Complete MCP/TimeTrackProject/timetrack mcp server/mcp-client-and-advanced/client/06_ping_and_errors.py | F48: 06 -- PING AND A REAL ERROR | G48: Looked through | H48: Covered | I48: 1 | J48: Measured: shared terms with the books | K48: agentic-ai:ch17 (9), agentic-ai:ch16 (6), agentic-ai:ch12 (5) | M48: Medium | N48: None | O48: Done | P48: 2026-10-31
A49: R-048 | B49: Course repo file | C49: Complete MCP | D49: 07_timeout_and_cancellation.py | E49: Complete MCP/TimeTrackProject/timetrack mcp server/mcp-client-and-advanced/client/07_timeout_and_cancellation.py | F49: 07 -- TIMEOUT, WHICH TRIGGERS A REAL CANCELLATION | G49: Looked through | H49: Covered | I49: 1 | J49: Measured: shared terms with the books | K49: agentic-ai:ch17 (7), agentic-ai:ch16 (7), agentic-ai:ch12 (5) | M49: Medium | N49: None | O49: Done | P49: 2026-10-31
A50: R-049 | B50: Course repo file | C50: Complete MCP | D50: 08_progress_notifications.py | E50: Complete MCP/TimeTrackProject/timetrack mcp server/mcp-client-and-advanced/client/08_progress_notifications.py | F50: 08 -- PROGRESS NOTIFICATIONS, WATCHED LIVE | G50: Looked through | H50: Covered | I50: 1 | J50: Measured: shared terms with the books | K50: agentic-ai:ch17 (9), agentic-ai:ch16 (6), agentic-ai:ch18 (5) | M50: Medium | N50: None | O50: Done | P50: 2026-10-31
A51: R-050 | B51: Course repo file | C51: Complete MCP | D51: database.py | E51: Complete MCP/TimeTrackProject/timetrack mcp server/mcp-client-and-advanced/database.py | F51: TimeTrack's persistence layer -- SQLite, shared by every tool in this | G51: Looked through | H51: Covered | I51: 1 | J51: Measured: shared terms with the books | K51: agentic-ai:ch16 (35), agentic-ai:ch15 (17), agentic-ai:ch17 (12) | M51: Medium | N51: None | O51: Done | P51: 2026-10-31
A52: R-051 | B52: Course repo file | C52: Complete MCP | D52: main.py | E52: Complete MCP/TimeTrackProject/timetrack mcp server/mcp-client-and-advanced/main.py | F52: main.py -- the COMPLETE TimeTrack server used by every file in client/. | G52: Looked through | H52: Covered | I52: 1 | J52: Measured: shared terms with the books | K52: agentic-ai:ch16 (30), agentic-ai:ch17 (19), agentic-ai:ch15 (16) | M52: Medium | N52: None | O52: Done | P52: 2026-10-31
A53: R-052 | B53: Course repo file | C53: Complete MCP | D53: pyproject.toml | E53: Complete MCP/TimeTrackProject/timetrack mcp server/mcp-client-and-advanced/pyproject.toml | F53: pyproject.toml | G53: Ignored | H53: No teaching content | J53: Measured: shared terms with the books | K53: agentic-ai:ch15, agentic-ai:ch16 | M53: Medium | N53: None | O53: Not needed | P53: 2026-10-31 | Q53: lock file, log, config or archive
A54: R-053 | B54: Course repo file | C54: Complete MCP | D54: mcp_htttp_connection.txt | E54: Complete MCP/TimeTrackProject/timetrack mcp server/mcp_htttp_connection.txt | F54: mcp_htttp_connection.txt | G54: Read properly | H54: Covered | J54: Measured: shared terms with the books | K54: agentic-ai:ch15, agentic-ai:ch16 | M54: Medium | N54: None | O54: Done | P54: 2026-10-31 | Q54: too little text to measure; a chapter links to it
A55: R-054 | B55: Course repo file | C55: Complete MCP | D55: pyproject.toml | E55: Complete MCP/TimeTrackProject/timetrack mcp server/pyproject.toml | F55: pyproject.toml | G55: Ignored | H55: No teaching content | J55: Measured: shared terms with the books | K55: agentic-ai:ch15, agentic-ai:ch16 | M55: Medium | N55: None | O55: Not needed | P55: 2026-10-31 | Q55: lock file, log, config or archive
A56: R-055 | B56: Course repo file | C56: Complete MCP | D56: concurrency_showcase.py | E56: Complete MCP/TimeTrackProject/timetrack mcp server/scripts/concurrency_showcase.py | F56: Concurrency + persistence showcase for a deployed TimeTrack MCP server. | G56: Looked through | H56: Partly covered | I56: 0.34615385 | J56: Measured: shared terms with the books | K56: agentic-ai:ch16 (8), agentic-ai:ch17 (6), agentic-ai:ch15 (5) | L56: uuid4, timetrack_test_n, timetrack_mcp_url, timed_log_time, serializing, seq_total, employee_for, default_url, conc_total, conc_results, bar_start, bar_end | M56: Medium | N56: Add the missing concepts to MCP chapters | O56: To do | P56: 2026-10-31
A57: R-056 | B57: Course repo file | C57: Complete MCP | D57: app.js | E57: Complete MCP/TimeTrackProject/timetrack mcp server/static/app.js | F57: app.js | G57: Looked through | H57: Partly covered | I57: 0.33333333 | J57: Measured: shared terms with the books | K57: agentic-ai:ch16 (5), agentic-ai:ch15 (4), agentic-ai:ch17 (3) | L57: queryselectorall, queryselector, parsefloat, loadprojectoptions, loadentries, escapehtml, encodeuricomponent, createelement, getelementbyid, foreach, addeventlistener, preventdefault | M57: Medium | N57: Add the missing concepts to MCP chapters | O57: To do | P57: 2026-10-31
A58: R-057 | B58: Course repo file | C58: Complete MCP | D58: index.html | E58: Complete MCP/TimeTrackProject/timetrack mcp server/static/index.html | F58: index.html | G58: Looked through | H58: Covered | J58: Measured: shared terms with the books | K58: agentic-ai:ch15, agentic-ai:ch16 | M58: Medium | N58: None | O58: Done | P58: 2026-10-31 | Q58: too little text to measure; a chapter links to it
A59: R-058 | B59: Course repo file | C59: Complete MCP | D59: style.css | E59: Complete MCP/TimeTrackProject/timetrack mcp server/static/style.css | F59: style.css | G59: Looked through | H59: Covered | J59: Measured: shared terms with the books | K59: agentic-ai:ch15, agentic-ai:ch16 | M59: Medium | N59: None | O59: Done | P59: 2026-10-31 | Q59: too little text to measure; a chapter links to it
A60: R-059 | B60: Course repo file | C60: Complete MCP | D60: steps_to_remote_mcp.txt | E60: Complete MCP/TimeTrackProject/timetrack mcp server/steps_to_remote_mcp.txt | F60: steps_to_remote_mcp.txt | G60: Read properly | H60: Covered | J60: Measured: shared terms with the books | K60: agentic-ai:ch15, agentic-ai:ch16 | M60: Medium | N60: None | O60: Done | P60: 2026-10-31 | Q60: too little text to measure; a chapter links to it
A61: R-060 | B61: Course repo file | C61: Complete MCP | D61: timetrack.db | E61: Complete MCP/TimeTrackProject/timetrack mcp server/timetrack.db | F61: timetrack.db | G61: Ignored | H61: No teaching content | J61: Measured: shared terms with the books | K61: agentic-ai:ch15, agentic-ai:ch16 | M61: Medium | N61: None | O61: Not needed | P61: 2026-10-31 | Q61: lock file, log, config or archive
A62: R-061 | B62: Course repo file | C62: Complete MCP | D62: uv.lock | E62: Complete MCP/TimeTrackProject/timetrack mcp server/uv.lock | F62: uv.lock | G62: Ignored | H62: No teaching content | J62: Measured: shared terms with the books | K62: agentic-ai:ch15, agentic-ai:ch16 | M62: Medium | N62: None | O62: Not needed | P62: 2026-10-31 | Q62: lock file, log, config or archive
A63: R-062 | B63: Course repo file | C63: Complete MCP | D63: timetrack_notebook.ipynb | E63: Complete MCP/TimeTrackProject/timetrack_notebook.ipynb | F63: TimeTrack: A Real, Professional Application With MCP Built In | G63: Looked through | H63: Covered | I63: 0.675 | J63: Measured: shared terms with the books | K63: agentic-ai:ch16 (26), agentic-ai:ch15 (18), agentic-ai:ch17 (8) | L63: heading: aggregation complexity verifi, heading: actual persistence proof, heading: checklist complete setup, new_entry, main_py_code, database_code, asha_sheet, serve_index, api_list_entries, fileresponse, api_project_summary, api_list_projects | M63: Medium | N63: None | O63: Done | P63: 2026-10-31
A64: R-063 | B64: Course repo file | C64: Complete MCP | D64: Why MCP Had to Exist.txt | E64: Complete MCP/Why MCP Had to Exist.txt | F64: Why MCP Had to Exist.txt | G64: Looked through | H64: No teaching content | J64: Measured: shared terms with the books | M64: Medium | N64: None | O64: Not needed | P64: 2026-10-31 | Q64: too little text to measure
A65: R-064 | B65: Course repo file | C65: Complete MCP | D65: claude_desktop_config.json | E65: Complete MCP/claude_desktop_config.json | F65: claude_desktop_config.json | G65: Looked through | H65: No teaching content | J65: Measured: shared terms with the books | M65: Medium | N65: None | O65: Not needed | P65: 2026-10-31 | Q65: too little text to measure
A66: R-065 | B66: Course repo file | C66: Complete MCP | D66: .python-version | E66: Complete MCP/first-mcp-server/.python-version | F66: .python-version | G66: Ignored | H66: No teaching content | J66: Measured: shared terms with the books | M66: Medium | N66: None | O66: Not needed | P66: 2026-10-31 | Q66: lock file, log, config or archive
A67: R-066 | B67: Course repo file | C67: Complete MCP | D67: README.md | E67: Complete MCP/first-mcp-server/README.md | F67: README.md | G67: Looked through | H67: No teaching content | J67: Measured: shared terms with the books | M67: Medium | N67: None | O67: Not needed | P67: 2026-10-31 | Q67: too little text to measure
A68: R-067 | B68: Course repo file | C68: Complete MCP | D68: Untitled-1.json | E68: Complete MCP/first-mcp-server/Untitled-1.json | F68: Untitled-1.json | G68: Looked through | H68: No teaching content | J68: Measured: shared terms with the books | M68: Medium | N68: None | O68: Not needed | P68: 2026-10-31 | Q68: too little text to measure
A69: R-068 | B69: Course repo file | C69: Complete MCP | D69: main.py | E69: Complete MCP/first-mcp-server/main.py | F69: main.py | G69: Looked through | H69: No teaching content | J69: Measured: shared terms with the books | M69: Medium | N69: None | O69: Not needed | P69: 2026-10-31 | Q69: too little text to measure
A70: R-069 | B70: Course repo file | C70: Complete MCP | D70: pyproject.toml | E70: Complete MCP/first-mcp-server/pyproject.toml | F70: pyproject.toml | G70: Ignored | H70: No teaching content | J70: Measured: shared terms with the books | M70: Medium | N70: None | O70: Not needed | P70: 2026-10-31 | Q70: lock file, log, config or archive
A71: R-070 | B71: Course repo file | C71: Complete MCP | D71: recipebox_fastmcp.py | E71: Complete MCP/first-mcp-server/recipebox_fastmcp.py | F71: recipebox_fastmcp.py | G71: Looked through | H71: Covered | I71: 0.91666667 | J71: Measured: shared terms with the books | K71: agentic-ai:ch14 (10), agentic-ai:ch11 (5), agentic-ai:ch12 (2) | L71: search_for_quick_recipes | M71: Medium | N71: None | O71: Done | P71: 2026-10-31
A72: R-071 | B72: Course repo file | C72: Complete MCP | D72: recipebox_lowlevel.py | E72: Complete MCP/first-mcp-server/recipebox_lowlevel.py | F72: RecipeBox -- built with the RAW, low-level official `mcp` SDK. | G72: Looked through | H72: Covered | I72: 0.86666667 | J72: Measured: shared terms with the books | K72: agentic-ai:ch14 (11), agentic-ai:ch16 (6), agentic-ai:ch11 (6) | L72: create_initialization_options, stdio_server | M72: Medium | N72: None | O72: Done | P72: 2026-10-31
A73: R-072 | B73: Course repo file | C73: Complete MCP | D73: uv.lock | E73: Complete MCP/first-mcp-server/uv.lock | F73: uv.lock | G73: Ignored | H73: No teaching content | J73: Measured: shared terms with the books | M73: Medium | N73: None | O73: Not needed | P73: 2026-10-31 | Q73: lock file, log, config or archive
A74: R-073 | B74: Course repo file | C74: Complete MCP | D74: link.txt | E74: Complete MCP/link.txt | F74: link.txt | G74: Looked through | H74: No teaching content | J74: Measured: shared terms with the books | M74: Medium | N74: None | O74: Not needed | P74: 2026-10-31 | Q74: too little text to measure
A75: R-074 | B75: Course repo file | C75: Complete MCP | D75: .gitignore | E75: Complete MCP/mcp-warmup/.gitignore | F75: .gitignore | G75: Ignored | H75: No teaching content | J75: Measured: shared terms with the books | M75: Medium | N75: None | O75: Not needed | P75: 2026-10-31 | Q75: lock file, log, config or archive
A76: R-075 | B76: Course repo file | C76: Complete MCP | D76: .python-version | E76: Complete MCP/mcp-warmup/.python-version | F76: .python-version | G76: Ignored | H76: No teaching content | J76: Measured: shared terms with the books | M76: Medium | N76: None | O76: Not needed | P76: 2026-10-31 | Q76: lock file, log, config or archive
A77: R-076 | B77: Course repo file | C77: Complete MCP | D77: README.md | E77: Complete MCP/mcp-warmup/README.md | F77: README.md | G77: Looked through | H77: No teaching content | J77: Measured: shared terms with the books | M77: Medium | N77: None | O77: Not needed | P77: 2026-10-31 | Q77: too little text to measure
A78: R-077 | B78: Course repo file | C78: Complete MCP | D78: mcp_server_with_primitives.py | E78: Complete MCP/mcp-warmup/mcp_server_with_primitives.py | F78: mcp_server_with_primitives.py | G78: Looked through | H78: Covered | I78: 1 | J78: Measured: shared terms with the books | K78: agentic-ai:ch12 (6) | M78: Medium | N78: None | O78: Done | P78: 2026-10-31
A79: R-078 | B79: Course repo file | C79: Complete MCP | D79: pyproject.toml | E79: Complete MCP/mcp-warmup/pyproject.toml | F79: pyproject.toml | G79: Ignored | H79: No teaching content | J79: Measured: shared terms with the books | M79: Medium | N79: None | O79: Not needed | P79: 2026-10-31 | Q79: lock file, log, config or archive
A80: R-079 | B80: Course repo file | C80: Complete MCP | D80: server.py | E80: Complete MCP/mcp-warmup/server.py | F80: server.py | G80: Looked through | H80: No teaching content | J80: Measured: shared terms with the books | K80: agentic-ai:ch11 (2), agentic-ai:ch16 (2) | M80: Medium | N80: None | O80: Not needed | P80: 2026-10-31 | Q80: too little text to measure
A81: R-080 | B81: Course repo file | C81: Complete MCP | D81: server_with_auth.py | E81: Complete MCP/mcp-warmup/server_with_auth.py | F81: server_with_auth.py | G81: Looked through | H81: Covered | I81: 1 | J81: Measured: shared terms with the books | K81: agentic-ai:ch16 (24), agentic-ai:ch18 (9), agentic-ai:ch11 (8) | M81: Medium | N81: None | O81: Done | P81: 2026-10-31
A82: R-081 | B82: Course repo file | C82: Complete MCP | D82: __init__.py | E82: Complete MCP/mcp-warmup/src/mcp_warmup/__init__.py | F82: __init__.py | G82: Ignored | H82: No teaching content | J82: Measured: shared terms with the books | M82: Medium | N82: None | O82: Not needed | P82: 2026-10-31 | Q82: lock file, log, config or archive
A83: R-082 | B83: Course repo file | C83: Complete MCP | D83: uv.lock | E83: Complete MCP/mcp-warmup/uv.lock | F83: uv.lock | G83: Ignored | H83: No teaching content | J83: Measured: shared terms with the books | M83: Medium | N83: None | O83: Not needed | P83: 2026-10-31 | Q83: lock file, log, config or archive
A84: R-083 | B84: Course repo file | C84: Complete MCP | D84: mcp.log | E84: Complete MCP/mcp.log | F84: mcp.log | G84: Ignored | H84: No teaching content | J84: Measured: shared terms with the books | M84: Medium | N84: None | O84: Not needed | P84: 2026-10-31 | Q84: lock file, log, config or archive
A85: R-084 | B85: Course repo file | C85: Complete MCP | D85: mcp_wiretap.py | E85: Complete MCP/mcp_wiretap.py | F85: mcp_wiretap.py — a universal wiretap for ANY real MCP server, not just a toy one. | G85: Looked through | H85: Partly covered | I85: 0.33333333 | J85: Measured: shared terms with the books | K85: agentic-ai:ch13 (11), agentic-ai:ch17 (9), agentic-ai:ch15 (9) | L85: use_color, store_true, pretty_json, no_color, colorize_json, colored_banner, c_str, c_server, c_punct, c_num, c_key, c_event | M85: Medium | N85: Add the missing concepts to MCP chapters | O85: To do | P85: 2026-10-31
A86: R-085 | B86: Course repo file | C86: Complete MCP | D86: mcp_wiretap_no_color.py | E86: Complete MCP/mcp_wiretap_no_color.py | F86: mcp_wiretap.py — a universal wiretap for ANY real MCP server, not just a toy one. | G86: Looked through | H86: Partly covered | I86: 0.54545455 | J86: Measured: shared terms with the books | K86: agentic-ai:ch13 (11), agentic-ai:ch15 (9), agentic-ai:ch16 (8) | L86: usage, remainder, relay_server_to_client, relay_client_to_server, real_command, pipe, parse_args, important, argumentparser, add_argument | M86: Medium | N86: Add the missing concepts to MCP chapters | O86: To do | P86: 2026-10-31
A87: R-086 | B87: Course repo file | C87: Complete MCP | D87: p2_MCP_Architecture.ipynb | E87: Complete MCP/p2_MCP_Architecture.ipynb | F87: MCP Architecture: Who Talks, and What They Can Offer | G87: Looked through | H87: Covered | I87: 0.81818182 | J87: Measured: shared terms with the books | K87: agentic-ai:ch11 (9), agentic-ai:ch14 (9), agentic-ai:ch16 (9) | L87: heading: proven tools, server_code | M87: Medium | N87: None | O87: Done | P87: 2026-10-31
A88: R-087 | B88: Course repo file | C88: Complete MCP | D88: v4a_primitives_notebook (3).ipynb | E88: Complete MCP/v4a_primitives_notebook (3).ipynb | F88: MCP Primitives: The Three Things a Server Can Offer | G88: Looked through | H88: Covered | I88: 0.77777778 | J88: Measured: shared terms with the books | K88: agentic-ai:ch12 (12), agentic-ai:ch11 (9), agentic-ai:ch15 (5) | L88: heading: github ground tools, prompt_definition, final_server_code, example_output | M88: Medium | N88: None | O88: Done | P88: 2026-10-31
A89: R-088 | B89: Course repo file | C89: Complete MCP | D89: wiretap-live.log | E89: Complete MCP/wiretap-live.log | F89: wiretap-live.log | G89: Ignored | H89: No teaching content | J89: Measured: shared terms with the books | M89: Medium | N89: None | O89: Not needed | P89: 2026-10-31 | Q89: lock file, log, config or archive
A90: R-089 | B90: Course repo file | C90: (repo root) | D90: GLOSSARY.md | E90: GLOSSARY.md | F90: 📖 Glossary — Agentic AI 3.0 | G90: Read properly | H90: Covered | I90: 1 | J90: Measured: shared terms with the books | K90: agentic-ai:cheat (18), agentic-ai:glossary (17), agentic-ai:ch7 (12) | M90: Medium | N90: None | O90: Done | P90: 2026-10-31
A91: R-090 | B91: Course repo file | C91: (repo root) | D91: PREREQUISITES.md | E91: PREREQUISITES.md | F91: 🧰 Prerequisites & First-Time Setup | G91: Read properly | H91: Covered | I91: 0.9 | J91: Measured: shared terms with the books | K91: agentic-ai:ch20 (8), foundations:f1 (7), agentic-ai:ch1 (6) | L91: gsk_your_real_key_here | M91: Medium | N91: None | O91: Done | P91: 2026-10-31
A92: R-091 | B92: Course repo file | C92: (repo root) | D92: README.md | E92: README.md | F92: 🚀 Live Class 2026 — Agentic AI 3.0 Specialization | G92: Read properly | H92: Covered | I92: 0.8 | J92: Measured: shared terms with the books | K92: agentic-ai:ch3 (6), agentic-ai:ch6 (6), foundations:f1 (5) | L92: heading: project recurr throughout, heading: organiz | M92: Medium | N92: None | O92: Done | P92: 2026-10-31
A93: R-092 | B93: Course repo file | C93: Weekend 00 - 20-21 Jun | D93: README.md | E93: Weekend 00 - 20-21 Jun/README.md | F93: 🗓️ Weekend 00 — 21 Jun — Course Induction | G93: Read properly | H93: No teaching content | J93: Measured: shared terms with the books | L93: heading: navigation weekend | M93: Medium | N93: None | O93: Not needed | P93: 2026-10-31 | Q93: too little text to measure
A94: R-093 | B94: Course repo file | C94: Weekend 01 - 27-28 Jun | D94: Class-1-Python-and-AI.pdf | E94: Weekend 01 - 27-28 Jun/01 - 27 Jun - Python Setup & API Basics/Class-1-Python-and-AI.pdf | F94: Class-1-Python-and-AI.pdf | G94: Looked through | H94: No teaching content | J94: Measured: shared terms with the books | M94: Medium | N94: None | O94: Not needed | P94: 2026-10-31 | Q94: too little text to measure
A95: R-094 | B95: Course repo file | C95: Weekend 01 - 27-28 Jun | D95: OOPS.py | E95: Weekend 01 - 27-28 Jun/01 - 27 Jun - Python Setup & API Basics/OOPS.py | F95: OOPS.py | G95: Looked through | H95: No teaching content | J95: Measured: shared terms with the books | M95: Medium | N95: None | O95: Not needed | P95: 2026-10-31 | Q95: too little text to measure
A96: R-095 | B96: Course repo file | C96: Weekend 01 - 27-28 Jun | D96: Python_foundamentals.py | E96: Weekend 01 - 27-28 Jun/01 - 27 Jun - Python Setup & API Basics/Python_foundamentals.py | F96: Python_foundamentals.py | G96: Looked through | H96: Covered | I96: 0.8 | J96: Measured: shared terms with the books | K96: pydantic:glossary (5), foundations:f1 (5), foundations:f3 (4) | L96: day_temp, is_raining | M96: Medium | N96: None | O96: Done | P96: 2026-10-31
A97: R-096 | B97: Course repo file | C97: Weekend 01 - 27-28 Jun | D97: README.md | E97: Weekend 01 - 27-28 Jun/01 - 27 Jun - Python Setup & API Basics/README.md | F97: 🐍 Class 01 — Python for AI: Dev Environment & Fundamentals | G97: Looked through | H97: Partly covered | I97: 0.42307692 | J97: Measured: shared terms with the books | K97: foundations:f4 (8), foundations:f3 (6), foundations:f1 (5) | L97: python_foundamentals, heading: agent fram fundamental vocabulary, heading: environment sett, tool_registry, oops, day_temp, converted_amount, get_current_time, fake_weather_data, heading: action items, is_raining, allowed_characters | M97: Medium | N97: Add the missing concepts to Foundations f1 or f4 | O97: To do | P97: 2026-10-31
A98: R-097 | B98: Course repo file | C98: Weekend 01 - 27-28 Jun | D98: currency.py | E98: Weekend 01 - 27-28 Jun/01 - 27 Jun - Python Setup & API Basics/currency.py | F98: currency.py | G98: Looked through | H98: Not covered | I98: 0.2 | J98: Measured: shared terms with the books | L98: converted_amount, to_currency, from_currency, raise_for_status | M98: Medium | N98: Read and add to Foundations f1 or f4 | O98: To do | P98: 2026-10-31
A99: R-098 | B99: Course repo file | C99: Weekend 01 - 27-28 Jun | D99: functions or tools.py | E99: Weekend 01 - 27-28 Jun/01 - 27 Jun - Python Setup & API Basics/functions or tools.py | F99: functions or tools.py | G99: Looked through | H99: No teaching content | J99: Measured: shared terms with the books | L99: get_current_time, fake_weather_data | M99: Medium | N99: None | O99: Not needed | P99: 2026-10-31 | Q99: too little text to measure
A100: R-099 | B100: Course repo file | C100: Weekend 01 - 27-28 Jun | D100: .python-version | E100: Weekend 01 - 27-28 Jun/01 - 27 Jun - Python Setup & API Basics/my-first-project/.python-version | F100: .python-version | G100: Ignored | H100: No teaching content | J100: Measured: shared terms with the books | M100: Medium | N100: None | O100: Not needed | P100: 2026-10-31 | Q100: lock file, log, config or archive
...

Sheet LEGEND
A1: How this sheet works
A2: One row per item | B2: Every file in the course repo, every page of the LangChain, MCP and Pydantic documentation, every Meridian slide chapter, every Craft page and attachment, every instructor site and other repo.
A3: Read status | B3: What I did with the item itself: Read properly / Read in full, Looked through, NOT READ, Ignored, Excluded by you, Skipped on purpose.
A4: Concept covered? | B4: Whether the concepts in the item are in the books. This is separate from Read status: a page can be unread but its concepts may still be in the books from class notes, and a page can be read but only partly covered.
A5: Covered | B5: At least 55% of the item's distinctive terms are in the relevant book (35% if a chapter links to it as a source).
A6: Partly covered | B6: 25% to 55% of its distinctive terms are in the books, or a chapter links to it. "Missing concepts" lists terms not found.
A7: Not covered | B7: Under 25% of its distinctive terms are in the books and no chapter links to it.
A8: No teaching content | B8: Lock files, config, images, job ads, or too little text to measure.
A9: Excluded by you | B9: Frontend material and the pages you asked me to drop.
A10: Not applicable | B10: Pages outside the LangChain book (LangGraph not started, other products, integrations, generated API reference).
A11: Overlap score | B11: Share of the item's top 40 distinctive terms found in the books. Terms are code names (functions, classes, settings) and heading phrases. Generic words are removed. The books searched depend on the topic: MCP pages against the MCP chapters (LangChain ch11 to ch18), Pydantic pages against the Pydantic book, LangChain pages against the LangChain book, Meridian against the RAG book and chapter 20.
A12: Method | B12: Measured = the term overlap above. Recorded = taken from my build notes (Craft, sites). Proxy = the repo copy of the same file was measured.
A13: Limits of the measure | B13: It finds missing names and headings, not wrong explanations. A high score means the concept is named and discussed, not that the explanation is complete. Code files score low when the book explains the idea in plain words without using the file's function names. Treat "Partly covered" as a prompt to look, not a verdict.
... A16: Sources of the documentation text | B16: MCP: github.com/modelcontextprotocol/modelcontextprotocol (docs, version 2026-07-28). Pydantic: github.com/pydantic/pydantic (docs folder, main branch, close to but not exactly the "latest" site). LangChain: github.com/langchain-ai/docs (src/oss). The page lists come from the sites' llms.txt indexes.
